README.md
setup.py
gappy/__init__.py
gappy/api.py
gappy/exception.py
gappy.egg-info/PKG-INFO
gappy.egg-info/SOURCES.txt
gappy.egg-info/dependency_links.txt
gappy.egg-info/requires.txt
gappy.egg-info/top_level.txt
test/test.py