Metadata-Version: 1.1
Name: gappy
Version: 0.4.3
Summary: Python framework for Gap Service API
Home-page: https://github.com/GapAPy/Gappy/
Author: Sadegh Yazdani, Hossein Jafarzadeh, Mostafa Asadi
Author-email: m.s.yazdani86@gmail.com
License: GPL
Project-URL: Source Code, https://github.com/GapAPy/Gappy/
Keywords: gap messenger bot api python wrapper
Platform: UNKNOWN
Classifier: Development Status :: 5 - Production/Stable
Classifier: Intended Audience :: Developers
Classifier: Topic :: Software Development :: Libraries :: Python Modules
Classifier: Topic :: Communications :: Chat
Classifier: License :: OSI Approved :: GNU General Public License (GPL)
Classifier: Programming Language :: Python :: 3.4
Classifier: Programming Language :: Python :: 3.5
Classifier: Programming Language :: Python :: 3.6
